dl_plus/extractors/un1def/rinsefm.py
dl_plus_extractor_un1def_rinsefm-0.2.0.dist-info/LICENSE
dl_plus_extractor_un1def_rinsefm-0.2.0.dist-info/METADATA
dl_plus_extractor_un1def_rinsefm-0.2.0.dist-info/WHEEL
dl_plus_extractor_un1def_rinsefm-0.2.0.dist-info/top_level.txt
dl_plus_extractor_un1def_rinsefm-0.2.0.dist-info/RECORD
